napari_roi/__init__.py
napari_roi/_roi.py
napari_roi/_roi_widget.py
napari_roi/_version.py
napari_roi/napari.yaml
napari_roi/qt/__init__.py
napari_roi/qt/_roi_layer_accessor.py
napari_roi/qt/_roi_table_model.py
napari_roi/qt/utils.py
napari_roi-0.1.8.dist-info/LICENSE
napari_roi-0.1.8.dist-info/METADATA
napari_roi-0.1.8.dist-info/WHEEL
napari_roi-0.1.8.dist-info/entry_points.txt
napari_roi-0.1.8.dist-info/top_level.txt
napari_roi-0.1.8.dist-info/RECORD
