Metadata-Version: 2.1
Name: napari-roi
Version: 0.1.8
Summary: Select regions of interest (ROIs) using napari
Home-page: https://github.com/BodenmillerGroup/napari-roi
Author: Jonas Windhager
Author-email: jonas@windhager.io
Maintainer: Milad Adibi
Maintainer-email: milad.adibi@uzh.ch
License: MIT
Project-URL: Bug Tracker, https://github.com/BodenmillerGroup/napari-roi/issues
Project-URL: Documentation, https://github.com/BodenmillerGroup/napari-roi#README.md
Project-URL: Source Code, https://github.com/BodenmillerGroup/napari-roi
Project-URL: User Support, https://github.com/BodenmillerGroup/napari-roi/issues
Classifier: Framework :: napari
Classifier: Operating System :: OS Independent
Classifier: Programming Language :: Python
Classifier: Programming Language :: Python :: 3
Classifier: Programming Language :: Python :: 3.8
Classifier: Programming Language :: Python :: 3.9
Classifier: Programming Language :: Python :: 3.10
Classifier: License :: OSI Approved :: MIT License
Requires-Python: >=3.8
License-File: LICENSE
Requires-Dist: numpy
Requires-Dist: pandas
Requires-Dist: qtpy
